LICENSE
MANIFEST.in
README.md
setup.py
django_sfp.egg-info/PKG-INFO
django_sfp.egg-info/SOURCES.txt
django_sfp.egg-info/dependency_links.txt
django_sfp.egg-info/not-zip-safe
django_sfp.egg-info/requires.txt
django_sfp.egg-info/top_level.txt
sfp/__init__.py
sfp/apps.py
sfp/schema..py